[{"id":"dc100c03.23eff","type":"websocket-listener","path":"/ws/count","wholemsg":"true"},{"id":"e6f397fd.190c68","type":"inject","name":"","topic":"counter","payload":"","payloadType":"date","repeat":"1","crontab":"","once":true,"x":175.1999969482422,"y":106,"z":"469f3c5d.b960c4","wires":[["fac3c8d2.053c38"]]},{"id":"fac3c8d2.053c38","type":"function","name":"Count up/down","func":"context.count = context.count || 0;\nif (context.count <= 0) context.dir = 1;\nif (context.count >= 100) context.dir = -1;\ncontext.count += context.dir;\nmsg.payload = context.count;\nreturn msg;","outputs":1,"x":326.20001220703125,"y":106,"z":"469f3c5d.b960c4","wires":[["5947d3de.a6b82c","cad23756.352dc8"]]},{"id":"5947d3de.a6b82c","type":"websocket out","name":"","server":"dc100c03.23eff","x":524.2000274658203,"y":106,"z":"469f3c5d.b960c4","wires":[]},{"id":"cad23756.352dc8","type":"debug","name":"","active":true,"console":"false","complete":"false","x":504.2000274658203,"y":214.1999969482422,"z":"469f3c5d.b960c4","wires":[]}]